fahr/__init__.py
fahr/cli.py
fahr/fahr.py
fahr-0.0.1.dist-info/LICENSE
fahr-0.0.1.dist-info/METADATA
fahr-0.0.1.dist-info/WHEEL
fahr-0.0.1.dist-info/entry_points.txt
fahr-0.0.1.dist-info/top_level.txt
fahr-0.0.1.dist-info/RECORD
