Metadata-Version: 2.1
Name: fahr
Version: 0.0.1
Summary: Tool for running remote machine learning jobs remotely.
Home-page: https://github.com/ResidentMario/fahr
Author: Aleksey Bilogur
Author-email: aleksey.bilogur@gmail.com
License: UNKNOWN
Download-URL: https://github.com/ResidentMario/fahr/tarball/0.0.1
Keywords: data,machine learning,data engineering
Platform: UNKNOWN
Requires-Dist: docker
Requires-Dist: jinja2
Requires-Dist: click
Provides-Extra: all
Requires-Dist: boto3 ; extra == 'all'
Requires-Dist: sagemaker ; extra == 'all'
Requires-Dist: kaggle ; extra == 'all'
Provides-Extra: develop
Requires-Dist: sphinx ; extra == 'develop'
Requires-Dist: sphinx-rtd-theme ; extra == 'develop'
Requires-Dist: boto3 ; extra == 'develop'
Requires-Dist: sagemaker ; extra == 'develop'
Requires-Dist: kaggle ; extra == 'develop'
Provides-Extra: kaggle
Requires-Dist: kaggle ; extra == 'kaggle'
Provides-Extra: sagemaker
Requires-Dist: boto3 ; extra == 'sagemaker'
Requires-Dist: sagemaker ; extra == 'sagemaker'
